README.rst
setup.py
pathdict/__init__.py
pathdict/collection.py
pathdict.egg-info/PKG-INFO
pathdict.egg-info/SOURCES.txt
pathdict.egg-info/dependency_links.txt
pathdict.egg-info/top_level.txt