Metadata-Version: 1.0
Name: pathdict
Version: 0.0.9
Summary: UNKNOWN
Home-page: https://github.com/diogommartins/pathdict
Author: Diogo Magalhaes Martins
Author-email: magalhaesmartins@icloud.com
License: UNKNOWN
Keywords: collection dictionary dict path dotted mongodb
Platform: UNKNOWN
